{"leaderboard": [{"placement": "1", "username": "abekat", "score": "1595", "features": "1514722893"}, {"placement": "2", "username": "abekat", "score": "1193", "features": "1514722893"}, {"placement": "3", "username": "abekat", "score": "989", "features": "1514722893"}, {"placement": "4", "username": "sasd", "score": "860", "features": "1514722893"}, {"placement": "5", "username": "abekat", "score": "781", "features": "1514722893"}, {"placement": "6", "username": "abekat", "score": "718", "features": "1514722893"}, {"placement": "7", "username": "abem", "score": "703", "features": "1050115781"}, {"placement": "8", "username": "abekt", "score": "627", "features": "432675521"}, {"placement": "9", "username": "abekt", "score": "627", "features": "432675521"}, {"placement": "10", "username": "abe", "score": "465", "features": "1164632385"}, {"placement": "11", "username": "abe", "score": "463", "features": "1164632385"}, {"placement": "12", "username": "abem", "score": "452", "features": "1050115781"}, {"placement": "13", "username": "abekat", "score": "424", "features": "1514722893"}, {"placement": "14", "username": "rip", "score": "405", "features": "514595408"}, {"placement": "15", "username": "akashot", "score": "403", "features": "321577539"}, {"placement": "16", "username": "rip", "score": "401", "features": "514595408"}, {"placement": "17", "username": "abe", "score": "394", "features": "99850621"}, {"placement": "18", "username": "abe", "score": "394", "features": "99850621"}, {"placement": "19", "username": "abe", "score": "324", "features": "1164632385"}, {"placement": "20", "username": "gan", "score": "319", "features": "1514722893"}, {"placement": "21", "username": "aben", "score": "308", "features": "663616957"}, {"placement": "22", "username": "abe", "score": "308", "features": "1164632385"}, {"placement": "23", "username": "rip", "score": "307", "features": "514595408"}, {"placement": "24", "username": "rip", "score": "301", "features": "514595408"}, {"placement": "25", "username": "test2", "score": "300", "features": "1514722893"}, {"placement": "26", "username": "test2", "score": "300", "features": "1514722893"}, {"placement": "27", "username": "rip", "score": "222", "features": "514595408"}, {"placement": "28", "username": "akashot", "score": "212", "features": "2096584901"}, {"placement": "29", "username": "aa", "score": "207", "features": "1164632385"}, {"placement": "30", "username": "akashot", "score": "206", "features": "2096584901"}, {"placement": "31", "username": "rip", "score": "202", "features": "514595408"}, {"placement": "32", "username": "akashot", "score": "202", "features": "2096584901"}, {"placement": "33", "username": "akashot", "score": "200", "features": "2096584901"}, {"placement": "34", "username": "abekat", "score": "150", "features": "1164632385"}, {"placement": "35", "username": "abekt", "score": "128", "features": "432675521"}, {"placement": "36", "username": "", "score": "118", "features": "1164632385"}, {"placement": "37", "username": "rip", "score": "116", "features": "514595408"}, {"placement": "38", "username": "rip", "score": "111", "features": "514595408"}, {"placement": "39", "username": "rip", "score": "107", "features": "514595408"}, {"placement": "40", "username": "akashot", "score": "107", "features": "321577539"}, {"placement": "41", "username": "abekat", "score": "103", "features": "-2126340076"}, {"placement": "42", "username": "abekat", "score": "102", "features": "-1309815780"}, {"placement": "43", "username": "akashot", "score": "102", "features": "321577539"}, {"placement": "44", "username": "rip", "score": "101", "features": "514595408"}, {"placement": "45", "username": "akashot", "score": "100", "features": "2096584901"}, {"placement": "46", "username": "akashot", "score": "100", "features": "2096584901"}, {"placement": "47", "username": "akashot", "score": "100", "features": "2096584901"}, {"placement": "48", "username": "akashot", "score": "100", "features": "2096584901"}, {"placement": "49", "username": "abekat", "score": "89", "features": "-1309815780"}, {"placement": "50", "username": "abekat", "score": "57", "features": "-1309815780"}, {"placement": "51", "username": "abekat", "score": "31", "features": "-1309815780"}, {"placement": "52", "username": "abekat", "score": "20", "features": "-2126340076"}, {"placement": "53", "username": "", "score": "18", "features": "-1213041900"}, {"placement": "54", "username": "aben", "score": "12", "features": "594054733"}, {"placement": "55", "username": "akashot", "score": "10", "features": "321577539"}, {"placement": "56", "username": "abekat", "score": "7", "features": "1164632385"}, {"placement": "57", "username": "pog", "score": "5", "features": "1164632385"}, {"placement": "58", "username": "aben", "score": "4", "features": "594054733"}, {"placement": "59", "username": "abekat", "score": "2", "features": "1164632385"}, {"placement": "60", "username": "abem", "score": "2", "features": "1050115781"}, {"placement": "61", "username": "akashot", "score": "1", "features": "321577539"}, {"placement": "62", "username": "akashot", "score": "1", "features": "321577539"}, {"placement": "63", "username": "dv", "score": "1", "features": "806762712"}, {"placement": "64", "username": "abekat", "score": "0", "features": "-2126340076"}, {"placement": "65", "username": "abekat", "score": "0", "features": "-2126340076"}, {"placement": "66", "username": "abekat", "score": "0", "features": "-2126340076"}, {"placement": "67", "username": "abekat", "score": "0", "features": "-2126340076"}, {"placement": "68", "username": "abekat", "score": "0", "features": "-2126340076"}, {"placement": "69", "username": "abekat", "score": "0", "features": "-2126340076"}, {"placement": "70", "username": "abekat", "score": "0", "features": "-2126340076"}, {"placement": "71", "username": "akashot", "score": "0", "features": "321577539"}, {"placement": "72", "username": "akashot", "score": "0", "features": "321577539"}, {"placement": "73", "username": "akashot", "score": "0", "features": "321577539"}, {"placement": "74", "username": "akashot", "score": "0", "features": "321577539"}, {"placement": "75", "username": "aben", "score": "0", "features": "594054733"}], "users": [{"username": "Test", "highScore": "10", "date": "08/01/2024"}, {"username": "Test2", "highScore": "10", "date": "08/01/2024"}, {"username": "abekat", "highScore": "7", "date": "13/01/2024"}, {"username": "abe45", "highScore": "15", "date": "11/01/2024"}, {"username": "s", "highScore": "832", "date": "11/01/2024"}, {"username": "sas", "highScore": "225", "date": "12/01/2024"}, {"username": "sasd", "highScore": "860", "date": "12/01/2024"}, {"username": "ssddda", "highScore": "16", "date": "12/01/2024"}, {"username": "asa", "highScore": "106", "date": "12/01/2024"}, {"username": "pogges", "highScore": "65", "date": "12/01/2024"}, {"username": "kbs", "highScore": "269", "date": "12/01/2024"}, {"username": "abe", "highScore": "308", "date": "13/01/2024"}, {"username": "garn", "highScore": "6", "date": "12/01/2024"}, {"username": "gan", "highScore": "319", "date": "12/01/2024"}, {"username": "kat", "highScore": "234", "date": "12/01/2024"}, {"username": "yoy", "highScore": "247", "date": "12/01/2024"}, {"username": "miases", "highScore": "26", "date": "12/01/2024"}, {"username": "gob", "highScore": "2", "date": "12/01/2024"}, {"username": "gon", "highScore": "593", "date": "12/01/2024"}, {"username": "abekt", "highScore": "627", "date": "12/01/2024"}, {"username": "kattemor", "highScore": "767", "date": "12/01/2024"}, {"username": "abemand", "highScore": "8", "date": "12/01/2024"}, {"username": "rip", "highScore": "0", "date": "12/01/2024"}, {"username": "akashot", "highScore": "206", "date": "12/01/2024"}, {"username": "aben", "highScore": "0", "date": "13/01/2024"}, {"username": "abem", "highScore": "2", "date": "13/01/2024"}, {"username": "pog", "highScore": "5", "date": "13/01/2024"}, {"username": "aa", "highScore": "207", "date": "13/01/2024"}, {"username": "dv", "highScore": "1", "date": "13/01/2024"}, {"username": "ajjjjj", "highScore": "1", "date": "13/01/2024"}, {"username": "abbbb", "highScore": "340", "date": "13/01/2024"}]}